Workbook

Sheet About_This_Data
A1: Field | B1: Value
A2: Company | B2: Lumina Living Pte Ltd - fictional Singapore home-living retailer; HR Shared Services case data
A3: Reporting date | B3: 46295
A4: Scope | B4: 120 Q3 2026 HR cases, five departments. All identities and records are synthetic.
A5: Meaning | B5: Cost_SGD is the recorded HR case handling cost of all statuses; not a budget or productivity claim.
A6: Rejoin | B6: This input is a deterministic checkpoint, not proof of your Copilot output.

Sheet HR_Cases
A1: Case_ID | B1: Department | C1: Request_Type | D1: Priority | E1: Status | F1: Assigned_To | G1: Opened_Date | H1: Due_Date | I1: Closed_Date | J1: Estimated_Hours | K1: Actual_Hours | L1: Cost_SGD | M1: Description
A2: HR-2026-0001 | B2: Retail Sales | C2: Leave Request | D2: Low | E2: Closed | F2: Aisha Tan | G2: 46290 | H2: 46297 | I2: 46295 | J2: 2 | K2: 1 | L2: 90 | M2: Leave Request employee case 001
A3: HR-2026-0002 | B3: Retail Sales | C3: Leave Request | D3: Medium | E3: Closed | F3: Ben Lim | G3: 46289 | H3: 46297 | I3: 46295 | J3: 3 | K3: 2 | L3: 125.5 | M3: Leave Request employee case 002
A4: HR-2026-0003 | B4: Retail Sales | C4: Leave Request | D4: High | E4: In Progress | F4: Chloe Goh | G4: 46288 | H4: 46297 | J4: 4 | K4: 0 | L4: 161 | M4: Leave Request employee case 003
A5: HR-2026-0004 | B5: Operations | C5: Leave Request | D5: Critical | E5: On Hold | F5: Daniel Lee | G5: 46287 | H5: 46297 | J5: 5 | K5: 0 | L5: 196.5 | M5: Leave Request employee case 004
A6: HR-2026-0005 | B6: Operations | C6: Training Request | D6: Low | E6: New | F6: Elena Ong | G6: 46286 | H6: 46297 | J6: 6 | K6: 0 | L6: 232 | M6: Training Request employee case 005
A7: HR-2026-0006 | B7: Operations | C7: Training Request | D7: Medium | E7: Closed | F7: Farid Rahman | G7: 46285 | H7: 46297 | I7: 46295 | J7: 7 | K7: 6 | L7: 267.5 | M7: Training Request employee case 006
A8: HR-2026-0007 | B8: Finance | C8: Training Request | D8: High | E8: Closed | F8: Grace Ng | G8: 46284 | H8: 46297 | I8: 46295 | J8: 8 | K8: 7 | L8: 303 | M8: Training Request employee case 007
A9: HR-2026-0008 | B9: Finance | C9: Training Request | D9: Critical | E9: On Hold | F9: Hari Kumar | G9: 46283 | H9: 46297 | J9: 2 | K9: 0 | L9: 338.5 | M9: Training Request employee case 008
A10: HR-2026-0009 | B10: Finance | C10: Onboarding | D10: Low | E10: New | F10: Aisha Tan | G10: 46282 | H10: 46297 | J10: 3 | K10: 0 | L10: 374 | M10: Onboarding employee case 009
A11: HR-2026-0010 | B11: Marketing | C11: Onboarding | D11: Medium | E11: Cancelled | F11: Ben Lim | G11: 46281 | H11: 46297 | J11: 4 | K11: 0 | L11: 409.5 | M11: Onboarding employee case 010
A12: HR-2026-0011 | B12: Marketing | C12: Onboarding | D12: High | E12: Closed | F12: Chloe Goh | G12: 46280 | H12: 46287 | I12: 46287 | J12: 5 | K12: 2 | L12: 445 | M12: Onboarding employee case 011
A13: HR-2026-0012 | B13: Marketing | C13: Onboarding | D13: Critical | E13: Closed | F13: Daniel Lee | G13: 46279 | H13: 46287 | I13: 46287 | J13: 6 | K13: 3 | L13: 480.5 | M13: Onboarding employee case 012
A14: HR-2026-0013 | B14: Technology | C14: Payroll Query | D14: Low | E14: New | G14: 46278 | H14: 46287 | J14: 7 | K14: 0 | L14: 516 | M14: Payroll Query employee case 013
A15: HR-2026-0014 | B15: Technology | C15: Payroll Query | D15: Medium | E15: Assigned | F15: Farid Rahman | G15: 46277 | H15: 46287 | J15: 8 | K15: 0 | L15: 90 | M15: Payroll Query employee case 014
A16: HR-2026-0015 | B16: Technology | C16: Payroll Query | D16: High | E16: In Progress | F16: Grace Ng | G16: 46276 | H16: 46287 | J16: 2 | K16: 0 | L16: 125.5 | M16: Payroll Query employee case 015
A17: HR-2026-0016 | B17: Retail Sales | C17: Payroll Query | D17: Critical | E17: Closed | F17: Hari Kumar | G17: 46275 | H17: 46287 | I17: 46288 | J17: 3 | K17: 7 | L17: 161 | M17: Payroll Query employee case 016
A18: HR-2026-0017 | B18: Retail Sales | C18: Benefits Claim | D18: Low | E18: Closed | F18: Aisha Tan | G18: 46274 | H18: 46287 | I18: 46288 | J18: 4 | K18: 8 | L18: 196.5 | M18: Benefits Claim employee case 017
A19: HR-2026-0018 | B19: Retail Sales | C19: Benefits Claim | D19: Medium | E19: Assigned | F19: Ben Lim | G19: 46273 | H19: 46287 | J19: 5 | K19: 0 | L19: 232 | M19: Benefits Claim employee case 018
A20: HR-2026-0019 | B20: Operations | C20: Benefits Claim | D20: High | E20: In Progress | F20: Chloe Goh | G20: 46272 | H20: 46287 | J20: 6 | K20: 0 | L20: 267.5 | M20: Benefits Claim employee case 019
A21: HR-2026-0020 | B21: Operations | C21: Benefits Claim | D21: Critical | E21: Cancelled | F21: Daniel Lee | G21: 46271 | H21: 46287 | J21: 7 | K21: 0 | L21: 303 | M21: Benefits Claim employee case 020
A22: HR-2026-0021 | B22: Operations | C22: Leave Request | D22: Low | E22: Closed | F22: Elena Ong | G22: 46270 | H22: 46277 | I22: 46279 | J22: 8 | K22: 3 | L22: 338.5 | M22: Leave Request employee case 021
A23: HR-2026-0022 | B23: Finance | C23: Leave Request | D23: Medium | E23: Closed | F23: Farid Rahman | G23: 46269 | H23: 46277 | I23: 46279 | J23: 2 | K23: 4 | L23: 374 | M23: Leave Request employee case 022
A24: HR-2026-0023 | B24: Finance | C24: Leave Request | D24: High | E24: In Progress | F24: Grace Ng | G24: 46268 | H24: 46277 | J24: 3 | K24: 0 | L24: 409.5 | M24: Leave Request employee case 023
A25: HR-2026-0024 | B25: Finance | C25: Leave Request | D25: Critical | E25: On Hold | F25: Hari Kumar | G25: 46267 | H25: 46277 | J25: 4 | K25: 0 | L25: 445 | M25: Leave Request employee case 024
A26: HR-2026-0025 | B26: Marketing | C26: Training Request | D26: Low | E26: New | G26: 46266 | H26: 46277 | J26: 5 | K26: 0 | L26: 480.5 | M26: Training Request employee case 025
A27: HR-2026-0026 | B27: Marketing | C27: Training Request | D27: Medium | E27: Closed | F27: Ben Lim | G27: 46265 | H27: 46277 | I27: 46275 | J27: 6 | K27: 8 | L27: 516 | M27: Training Request employee case 026
A28: HR-2026-0027 | B28: Marketing | C28: Training Request | D28: High | E28: Closed | F28: Chloe Goh | G28: 46264 | H28: 46277 | I28: 46275 | J28: 7 | K28: 9 | L28: 90 | M28: Training Request employee case 027
A29: HR-2026-0028 | B29: Technology | C29: Training Request | D29: Critical | E29: On Hold | F29: Daniel Lee | G29: 46263 | H29: 46277 | J29: 8 | K29: 0 | L29: 125.5 | M29: Training Request employee case 028
A30: HR-2026-0029 | B30: Technology | C30: Onboarding | D30: Low | E30: New | F30: Elena Ong | G30: 46262 | H30: 46277 | J30: 2 | K30: 0 | L30: 161 | M30: Onboarding employee case 029
A31: HR-2026-0030 | B31: Technology | C31: Onboarding | D31: Medium | E31: Cancelled | F31: Farid Rahman | G31: 46261 | H31: 46277 | J31: 3 | K31: 0 | L31: 196.5 | M31: Onboarding employee case 030
A32: HR-2026-0031 | B32: Retail Sales | C32: Onboarding | D32: High | E32: Closed | F32: Grace Ng | G32: 46260 | H32: 46267 | I32: 46266 | J32: 4 | K32: 4 | L32: 232 | M32: Onboarding employee case 031
A33: HR-2026-0032 | B33: Retail Sales | C33: Onboarding | D33: Critical | E33: Closed | F33: Hari Kumar | G33: 46259 | H33: 46267 | I33: 46266 | J33: 5 | K33: 5 | L33: 267.5 | M33: Onboarding employee case 032
A34: HR-2026-0033 | B34: Retail Sales | C34: Payroll Query | D34: Low | E34: New | F34: Aisha Tan | G34: 46258 | H34: 46267 | J34: 6 | K34: 0 | L34: 303 | M34: Payroll Query employee case 033
A35: HR-2026-0034 | B35: Operations | C35: Payroll Query | D35: Medium | E35: Assigned | F35: Ben Lim | G35: 46257 | H35: 46267 | J35: 7 | K35: 0 | L35: 338.5 | M35: Payroll Query employee case 034
A36: HR-2026-0035 | B36: Operations | C36: Payroll Query | D36: High | E36: In Progress | F36: Chloe Goh | G36: 46256 | H36: 46267 | J36: 8 | K36: 0 | L36: 374 | M36: Payroll Query employee case 035
A37: HR-2026-0036 | B37: Operations | C37: Payroll Query | D37: Critical | E37: Closed | F37: Daniel Lee | G37: 46255 | H37: 46267 | I37: 46267 | J37: 2 | K37: 9 | L37: 409.5 | M37: Payroll Query employee case 036
A38: HR-2026-0037 | B38: Finance | C38: Benefits Claim | D38: Low | E38: Closed | F38: Elena Ong | G38: 46254 | H38: 46267 | I38: 46267 | J38: 3 | K38: 1 | L38: 445 | M38: Benefits Claim employee case 037
A39: HR-2026-0038 | B39: Finance | C39: Benefits Claim | D39: Medium | E39: Assigned | F39: Farid Rahman | G39: 46253 | H39: 46267 | J39: 4 | K39: 0 | L39: 480.5 | M39: Benefits Claim employee case 038
A40: HR-2026-0039 | B40: Finance | C40: Benefits Claim | D40: High | E40: In Progress | F40: Grace Ng | G40: 46252 | H40: 46267 | J40: 5 | K40: 0 | L40: 516 | M40: Benefits Claim employee case 039
A41: HR-2026-0040 | B41: Marketing | C41: Benefits Claim | D41: Critical | E41: Cancelled | F41: Hari Kumar | G41: 46251 | H41: 46267 | J41: 6 | K41: 0 | L41: 90 | M41: Benefits Claim employee case 040
A42: HR-2026-0041 | B42: Marketing | C42: Leave Request | D42: Low | E42: Closed | F42: Aisha Tan | G42: 46250 | H42: 46257 | I42: 46258 | J42: 7 | K42: 5 | L42: 125.5 | M42: Leave Request employee case 041
A43: HR-2026-0042 | B43: Marketing | C43: Leave Request | D43: Medium | E43: Closed | F43: Ben Lim | G43: 46249 | H43: 46257 | I43: 46258 | J43: 8 | K43: 6 | L43: 161 | M43: Leave Request employee case 042
A44: HR-2026-0043 | B44: Technology | C44: Leave Request | D44: High | E44: In Progress | F44: Chloe Goh | G44: 46248 | H44: 46257 | J44: 2 | K44: 0 | L44: 196.5 | M44: Leave Request employee case 043
A45: HR-2026-0044 | B45: Technology | C45: Leave Request | D45: Critical | E45: On Hold | F45: Daniel Lee | G45: 46247 | H45: 46257 | J45: 3 | K45: 0 | L45: 232 | M45: Leave Request employee case 044
A46: HR-2026-0045 | B46: Technology | C46: Training Request | D46: Low | E46: New | F46: Elena Ong | G46: 46246 | H46: 46257 | J46: 4 | K46: 0 | L46: 267.5 | M46: Training Request employee case 045
A47: HR-2026-0046 | B47: Retail Sales | C47: Training Request | D47: Medium | E47: Closed | F47: Farid Rahman | G47: 46245 | H47: 46257 | I47: 46259 | J47: 5 | K47: 1 | L47: 303 | M47: Training Request employee case 046
A48: HR-2026-0047 | B48: Retail Sales | C48: Training Request | D48: High | E48: Closed | F48: Grace Ng | G48: 46244 | H48: 46257 | I48: 46259 | J48: 6 | K48: 2 | L48: 338.5 | M48: Training Request employee case 047
A49: HR-2026-0048 | B49: Retail Sales | C49: Training Request | D49: Critical | E49: On Hold | F49: Hari Kumar | G49: 46243 | H49: 46257 | J49: 7 | K49: 0 | L49: 374 | M49: Training Request employee case 048
A50: HR-2026-0049 | B50: Operations | C50: Onboarding | D50: Low | E50: New | G50: 46242 | H50: 46257 | J50: 8 | K50: 0 | L50: 409.5 | M50: Onboarding employee case 049
A51: HR-2026-0050 | B51: Operations | C51: Onboarding | D51: Medium | E51: Cancelled | F51: Ben Lim | G51: 46241 | H51: 46257 | J51: 2 | K51: 0 | L51: 445 | M51: Onboarding employee case 050
A52: HR-2026-0051 | B52: Operations | C52: Onboarding | D52: High | E52: Closed | F52: Chloe Goh | G52: 46240 | H52: 46247 | I52: 46245 | J52: 3 | K52: 6 | L52: 480.5 | M52: Onboarding employee case 051
A53: HR-2026-0052 | B53: Finance | C53: Onboarding | D53: Critical | E53: Closed | F53: Daniel Lee | G53: 46239 | H53: 46247 | I53: 46245 | J53: 4 | K53: 7 | L53: 516 | M53: Onboarding employee case 052
A54: HR-2026-0053 | B54: Finance | C54: Payroll Query | D54: Low | E54: New | F54: Elena Ong | G54: 46238 | H54: 46247 | J54: 5 | K54: 0 | L54: 90 | M54: Payroll Query employee case 053
A55: HR-2026-0054 | B55: Finance | C55: Payroll Query | D55: Medium | E55: Assigned | F55: Farid Rahman | G55: 46237 | H55: 46247 | J55: 6 | K55: 0 | L55: 125.5 | M55: Payroll Query employee case 054
A56: HR-2026-0055 | B56: Marketing | C56: Payroll Query | D56: High | E56: In Progress | F56: Grace Ng | G56: 46236 | H56: 46247 | J56: 7 | K56: 0 | L56: 161 | M56: Payroll Query employee case 055
A57: HR-2026-0056 | B57: Marketing | C57: Payroll Query | D57: Critical | E57: Closed | F57: Hari Kumar | G57: 46235 | H57: 46247 | I57: 46246 | J57: 8 | K57: 2 | L57: 196.5 | M57: Payroll Query employee case 056
A58: HR-2026-0057 | B58: Marketing | C58: Benefits Claim | D58: Low | E58: Closed | F58: Aisha Tan | G58: 46234 | H58: 46247 | I58: 46246 | J58: 2 | K58: 3 | L58: 232 | M58: Benefits Claim employee case 057
A59: HR-2026-0058 | B59: Technology | C59: Benefits Claim | D59: Medium | E59: Assigned | F59: Ben Lim | G59: 46233 | H59: 46247 | J59: 3 | K59: 0 | L59: 267.5 | M59: Benefits Claim employee case 058
A60: HR-2026-0059 | B60: Technology | C60: Benefits Claim | D60: High | E60: In Progress | F60: Chloe Goh | G60: 46232 | H60: 46247 | J60: 4 | K60: 0 | L60: 303 | M60: Benefits Claim employee case 059
A61: HR-2026-0060 | B61: Technology | C61: Benefits Claim | D61: Critical | E61: Cancelled | F61: Daniel Lee | G61: 46231 | H61: 46247 | J61: 5 | K61: 0 | L61: 338.5 | M61: Benefits Claim employee case 060
A62: HR-2026-0061 | B62: Retail Sales | C62: Leave Request | D62: Low | E62: Closed | F62: Elena Ong | G62: 46230 | H62: 46237 | I62: 46237 | J62: 6 | K62: 7 | L62: 374 | M62: Leave Request employee case 061
A63: HR-2026-0062 | B63: Retail Sales | C63: Leave Request | D63: Medium | E63: Closed | F63: Farid Rahman | G63: 46229 | H63: 46237 | I63: 46237 | J63: 7 | K63: 8 | L63: 409.5 | M63: Leave Request employee case 062
A64: HR-2026-0063 | B64: Retail Sales | C64: Leave Request | D64: High | E64: In Progress | F64: Grace Ng | G64: 46228 | H64: 46237 | J64: 8 | K64: 0 | L64: 445 | M64: Leave Request employee case 063
A65: HR-2026-0064 | B65: Operations | C65: Leave Request | D65: Critical | E65: On Hold | F65: Hari Kumar | G65: 46227 | H65: 46237 | J65: 2 | K65: 0 | L65: 480.5 | M65: Leave Request employee case 064
A66: HR-2026-0065 | B66: Operations | C66: Training Request | D66: Low | E66: New | F66: Aisha Tan | G66: 46226 | H66: 46237 | J66: 3 | K66: 0 | L66: 516 | M66: Training Request employee case 065
A67: HR-2026-0066 | B67: Operations | C67: Training Request | D67: Medium | E67: Closed | F67: Ben Lim | G67: 46225 | H67: 46237 | I67: 46238 | J67: 4 | K67: 3 | L67: 90 | M67: Training Request employee case 066
A68: HR-2026-0067 | B68: Finance | C68: Training Request | D68: High | E68: Closed | F68: Chloe Goh | G68: 46224 | H68: 46237 | I68: 46238 | J68: 5 | K68: 4 | L68: 125.5 | M68: Training Request employee case 067
A69: HR-2026-0068 | B69: Finance | C69: Training Request | D69: Critical | E69: On Hold | F69: Daniel Lee | G69: 46223 | H69: 46237 | J69: 6 | K69: 0 | L69: 161 | M69: Training Request employee case 068
A70: HR-2026-0069 | B70: Finance | C70: Onboarding | D70: Low | E70: New | F70: Elena Ong | G70: 46222 | H70: 46237 | J70: 7 | K70: 0 | L70: 196.5 | M70: Onboarding employee case 069
A71: HR-2026-0070 | B71: Marketing | C71: Onboarding | D71: Medium | E71: Cancelled | F71: Farid Rahman | G71: 46221 | H71: 46237 | J71: 8 | K71: 0 | L71: 232 | M71: Onboarding employee case 070
A72: HR-2026-0071 | B72: Marketing | C72: Onboarding | D72: High | E72: Closed | F72: Grace Ng | G72: 46220 | H72: 46227 | I72: 46229 | J72: 2 | K72: 8 | L72: 267.5 | M72: Onboarding employee case 071
A73: HR-2026-0072 | B73: Marketing | C73: Onboarding | D73: Critical | E73: Closed | F73: Hari Kumar | G73: 46219 | H73: 46227 | I73: 46229 | J73: 3 | K73: 9 | L73: 303 | M73: Onboarding employee case 072
A74: HR-2026-0073 | B74: Technology | C74: Payroll Query | D74: Low | E74: New | G74: 46218 | H74: 46227 | J74: 4 | K74: 0 | L74: 338.5 | M74: Payroll Query employee case 073
A75: HR-2026-0074 | B75: Technology | C75: Payroll Query | D75: Medium | E75: Assigned | F75: Ben Lim | G75: 46217 | H75: 46227 | J75: 5 | K75: 0 | L75: 374 | M75: Payroll Query employee case 074
A76: HR-2026-0075 | B76: Technology | C76: Payroll Query | D76: High | E76: In Progress | F76: Chloe Goh | G76: 46216 | H76: 46227 | J76: 6 | K76: 0 | L76: 409.5 | M76: Payroll Query employee case 075
A77: HR-2026-0076 | B77: Retail Sales | C77: Payroll Query | D77: Critical | E77: Closed | F77: Daniel Lee | G77: 46215 | H77: 46227 | I77: 46225 | J77: 7 | K77: 4 | L77: 445 | M77: Payroll Query employee case 076
A78: HR-2026-0077 | B78: Retail Sales | C78: Benefits Claim | D78: Low | E78: Closed | F78: Elena Ong | G78: 46214 | H78: 46227 | I78: 46225 | J78: 8 | K78: 5 | L78: 480.5 | M78: Benefits Claim employee case 077
A79: HR-2026-0078 | B79: Retail Sales | C79: Benefits Claim | D79: Medium | E79: Assigned | F79: Farid Rahman | G79: 46213 | H79: 46227 | J79: 2 | K79: 0 | L79: 516 | M79: Benefits Claim employee case 078
A80: HR-2026-0079 | B80: Operations | C80: Benefits Claim | D80: High | E80: In Progress | F80: Grace Ng | G80: 46212 | H80: 46227 | J80: 3 | K80: 0 | L80: 90 | M80: Benefits Claim employee case 079
A81: HR-2026-0080 | B81: Operations | C81: Benefits Claim | D81: Critical | E81: Cancelled | F81: Hari Kumar | G81: 46211 | H81: 46227 | J81: 4 | K81: 0 | L81: 125.5 | M81: Benefits Claim employee case 080
A82: HR-2026-0081 | B82: Operations | C82: Leave Request | D82: Low | E82: Closed | F82: Aisha Tan | G82: 46290 | H82: 46297 | I82: 46295 | J82: 5 | K82: 9 | L82: 161 | M82: Leave Request employee case 081
A83: HR-2026-0082 | B83: Finance | C83: Leave Request | D83: Medium | E83: Closed | F83: Ben Lim | G83: 46289 | H83: 46297 | I83: 46295 | J83: 6 | K83: 1 | L83: 196.5 | M83: Leave Request employee case 082
A84: HR-2026-0083 | B84: Finance | C84: Leave Request | D84: High | E84: In Progress | F84: Chloe Goh | G84: 46288 | H84: 46297 | J84: 7 | K84: 0 | L84: 232 | M84: Leave Request employee case 083
A85: HR-2026-0084 | B85: Finance | C85: Leave Request | D85: Critical | E85: On Hold | F85: Daniel Lee | G85: 46287 | H85: 46297 | J85: 8 | K85: 0 | L85: 267.5 | M85: Leave Request employee case 084
A86: HR-2026-0085 | B86: Marketing | C86: Training Request | D86: Low | E86: New | G86: 46286 | H86: 46297 | J86: 2 | K86: 0 | L86: 303 | M86: Training Request employee case 085
A87: HR-2026-0086 | B87: Marketing | C87: Training Request | D87: Medium | E87: Closed | F87: Farid Rahman | G87: 46285 | H87: 46297 | I87: 46295 | J87: 3 | K87: 5 | L87: 338.5 | M87: Training Request employee case 086
A88: HR-2026-0087 | B88: Marketing | C88: Training Request | D88: High | E88: Closed | F88: Grace Ng | G88: 46284 | H88: 46297 | I88: 46295 | J88: 4 | K88: 6 | L88: 374 | M88: Training Request employee case 087
A89: HR-2026-0088 | B89: Technology | C89: Training Request | D89: Critical | E89: On Hold | F89: Hari Kumar | G89: 46283 | H89: 46297 | J89: 5 | K89: 0 | L89: 409.5 | M89: Training Request employee case 088
A90: HR-2026-0089 | B90: Technology | C90: Onboarding | D90: Low | E90: New | F90: Aisha Tan | G90: 46282 | H90: 46297 | J90: 6 | K90: 0 | L90: 445 | M90: Onboarding employee case 089
A91: HR-2026-0090 | B91: Technology | C91: Onboarding | D91: Medium | E91: Cancelled | F91: Ben Lim | G91: 46281 | H91: 46297 | J91: 7 | K91: 0 | L91: 480.5 | M91: Onboarding employee case 090
A92: HR-2026-0091 | B92: Retail Sales | C92: Onboarding | D92: High | E92: Closed | F92: Chloe Goh | G92: 46280 | H92: 46287 | I92: 46288 | J92: 8 | K92: 1 | L92: 516 | M92: Onboarding employee case 091
A93: HR-2026-0092 | B93: Retail Sales | C93: Onboarding | D93: Critical | E93: Closed | F93: Daniel Lee | G93: 46279 | H93: 46287 | I93: 46288 | J93: 2 | K93: 2 | L93: 90 | M93: Onboarding employee case 092
A94: HR-2026-0093 | B94: Retail Sales | C94: Payroll Query | D94: Low | E94: New | F94: Elena Ong | G94: 46278 | H94: 46287 | J94: 3 | K94: 0 | L94: 125.5 | M94: Payroll Query employee case 093
A95: HR-2026-0094 | B95: Operations | C95: Payroll Query | D95: Medium | E95: Assigned | F95: Farid Rahman | G95: 46277 | H95: 46287 | J95: 4 | K95: 0 | L95: 161 | M95: Payroll Query employee case 094
A96: HR-2026-0095 | B96: Operations | C96: Payroll Query | D96: High | E96: In Progress | F96: Grace Ng | G96: 46276 | H96: 46287 | J96: 5 | K96: 0 | L96: 196.5 | M96: Payroll Query employee case 095
A97: HR-2026-0096 | B97: Operations | C97: Payroll Query | D97: Critical | E97: Closed | F97: Hari Kumar | G97: 46275 | H97: 46287 | I97: 46289 | J97: 6 | K97: 6 | L97: 232 | M97: Payroll Query employee case 096
A98: HR-2026-0097 | B98: Finance | C98: Benefits Claim | D98: Low | E98: Closed | F98: Aisha Tan | G98: 46274 | H98: 46287 | I98: 46289 | J98: 7 | K98: 7 | L98: 267.5 | M98: Benefits Claim employee case 097
A99: HR-2026-0098 | B99: Finance | C99: Benefits Claim | D99: Medium | E99: Assigned | F99: Ben Lim | G99: 46273 | H99: 46287 | J99: 8 | K99: 0 | L99: 303 | M99: Benefits Claim employee case 098
A100: HR-2026-0099 | B100: Finance | C100: Benefits Claim | D100: High | E100: In Progress | F100: Chloe Goh | G100: 46272 | H100: 46287 | J100: 2 | K100: 0 | L100: 338.5 | M100: Benefits Claim employee case 099
...

Sheet HR_Officers
A1: HR_Officer | B1: Primary_Category | C1: Available_Hours_Week | D1: Home_Department
A2: Aisha Tan | B2: Leave Request | C2: 35 | D2: Retail Sales
A3: Ben Lim | B3: Leave Request | C3: 30 | D3: Operations
A4: Chloe Goh | B4: Leave Request | C4: 35 | D4: Finance
A5: Daniel Lee | B5: Leave Request | C5: 30 | D5: Marketing
A6: Elena Ong | B6: Training Request | C6: 35 | D6: Technology
A7: Farid Rahman | B7: Training Request | C7: 30 | D7: Retail Sales
A8: Grace Ng | B8: Training Request | C8: 35 | D8: Operations
A9: Hari Kumar | B9: Training Request | C9: 30 | D9: Finance

Sheet Control
A1: Metric | B1: Expected / control
A2: Report_Date | B2: 46295
A3: total | B3: 120
A4: closed | B4: 48
A5: cancelled | B5: 12
A6: backlog | B6: 60
A7: overdue | B7: 50
A8: unassigned_backlog | B8: 6
A9: on_time_closed | B9: 30
A10: on_time_rate | B10: 0.625
A11: cost | B11: 35827.5
A12: Backlog definition | B12: Status is neither Closed nor Cancelled
A13: Overdue definition | B13: Backlog and Due_Date strictly earlier than Report_Date
A14: On-time definition | B14: Closed_Date <= Due_Date; denominator Closed only
A15: Unknown assignment | B15: Blank Assigned_To stays blank; propose separately

Sheet Prompt_Log
A1: Step | B1: App / mode | C1: Prompt | D1: What Copilot did | E1: How I verified | F1: Decision

Sheet Checks
A1: Check | B1: Formula / evidence | C1: Result
A2: Total clean rows | B2: =ROWS(tblHRCases[Case_ID])

Sheet .Rules
A1: ## SOURCE AND SCOPE
A2: Preserve HR_Cases, tblHRCases, HR_Officers, current Assigned_To values and source IDs.
A3: Use the reporting date from Control!B2. State the selected Department, Request_Type, Status and Assigned_To scope beside every report.
A4: Backlog excludes Closed and Cancelled. Overdue backlog has Due_Date strictly before Control!B2.
A5: On-time closure rate uses Closed rows only, with Closed_Date <= Due_Date. Display N/A when no Closed rows remain.
A6: ## FORMATS AND VISUALS
A7: Display recorded Cost_SGD as S$ with two decimals; keep underlying values exact. Show dates as DD-MMM-YYYY.
A8: Use white backgrounds, navy titles, blue and teal accents, readable labels and named units; never use colour alone.
A9: ## OUTPUT AND REVIEW
A10: Use structured table references. Preserve the visible .Rules sheet and unrelated sheets, charts and Prompt_Log.
A11: Keep current owners separate from unapproved assignment proposals. Missing facts and approvals remain UNKNOWN.
A12: Ask before replacing named output sheets. Reconcile every count, rate and chart against source rows; do not duplicate outputs on rerun.
A13: ="Reporting date: "&TEXT(Control!B2,"yyyy-mm-dd")

Sheet Pareto_Request_Type
A1: Request_Type | B1: Count | C1: Cumulative_Count | D1: Share | E1: Cumulative_Percent
A2: Payroll Query | B2: =COUNTIFS(tblHRCases[Request_Type],A2,tblHRCases[Status],"<>Closed",tblHRCases[Status],"<>Cancelled",tblHRCases[Due_Date],"<"&Control!$B$2) | C2: =SUM($B$2:B2) | D2: =IF(SUM($B$2:$B$6)=0,"N/A",B2/SUM($B$2:$B$6)) | E2: =IF(SUM($B$2:$B$6)=0,"N/A",C2/SUM($B$2:$B$6))
A3: Benefits Claim | B3: =COUNTIFS(tblHRCases[Request_Type],A3,tblHRCases[Status],"<>Closed",tblHRCases[Status],"<>Cancelled",tblHRCases[Due_Date],"<"&Control!$B$2) | C3: =SUM($B$2:B3) | D3: =IF(SUM($B$2:$B$6)=0,"N/A",B3/SUM($B$2:$B$6)) | E3: =IF(SUM($B$2:$B$6)=0,"N/A",C3/SUM($B$2:$B$6))
A4: Leave Request | B4: =COUNTIFS(tblHRCases[Request_Type],A4,tblHRCases[Status],"<>Closed",tblHRCases[Status],"<>Cancelled",tblHRCases[Due_Date],"<"&Control!$B$2) | C4: =SUM($B$2:B4) | D4: =IF(SUM($B$2:$B$6)=0,"N/A",B4/SUM($B$2:$B$6)) | E4: =IF(SUM($B$2:$B$6)=0,"N/A",C4/SUM($B$2:$B$6))
A5: Training Request | B5: =COUNTIFS(tblHRCases[Request_Type],A5,tblHRCases[Status],"<>Closed",tblHRCases[Status],"<>Cancelled",tblHRCases[Due_Date],"<"&Control!$B$2) | C5: =SUM($B$2:B5) | D5: =IF(SUM($B$2:$B$6)=0,"N/A",B5/SUM($B$2:$B$6)) | E5: =IF(SUM($B$2:$B$6)=0,"N/A",C5/SUM($B$2:$B$6))
A6: Onboarding | B6: =COUNTIFS(tblHRCases[Request_Type],A6,tblHRCases[Status],"<>Closed",tblHRCases[Status],"<>Cancelled",tblHRCases[Due_Date],"<"&Control!$B$2) | C6: =SUM($B$2:B6) | D6: =IF(SUM($B$2:$B$6)=0,"N/A",B6/SUM($B$2:$B$6)) | E6: =IF(SUM($B$2:$B$6)=0,"N/A",C6/SUM($B$2:$B$6))
A8: Reporting date | B8: =Control!B2
A9: Scope | B9: All; overdue backlog only
A10: Interpretation | B10: Four categories first reach80%; counts show contribution, not cause.
