Workbook

Sheet Connected_Workflow
A1: Field | B1: Value
A2: Company | B2: Lumina Living Pte Ltd
A3: Project | B3: SW-2026 Sustainable Workspace Launch
A4: Role | B4: Finance calculations
A5: Source | B5: Lumina-Business-Data.xlsx
A6: Output | B6: Lumina-Analysis.xlsx
A7: Status | B7: Illustrative comparison only; learner must record actual evidence
A8: Goal | B8: From Campaign_Data, calculate revenue, cost, margin, conversion and return rates using formulas. Define the denominator for each rate. Check 96 source records and handle zero denominators explicitly.
A9: Context | B9: You work for Lumina Living Pte Ltd on SW-2026, the Sustainable Workspace Launch. HR, Marketing, Finance and Operations share one evidence trail. Launch is planned for 1 October 2026; budget SGD 18,000; target 120 qualified enquiries.
A10: Source | B10: Lumina-Business-Data.xlsx. Use your own reviewed prior-lab files first; scenario/ contains supplied fallback examples.
A11: Expectations | B11: Save Lumina-Analysis.xlsx. Record source version, verified facts, unresolved questions and reviewer in Lumina-Living-Lab-06.xlsx. Keep projectSW-2026 and action IDsA01–A04 unchanged. Label every output Draft until reviewed; record actual app actions separately.

Sheet Scenario
A1: Lab 06: Build and Audit Excel Formulas with Copilot
A2: Lumina Living Pte Ltd · Sustainable Workspace campaign
A4: Topic | B4: 2
A5: Level | B5: Foundation
A6: Primary apps | B6: Excel + Copilot
A7: Goal | B7: Use Copilot to propose calculated columns while retaining formula transparency and controls.
A8: Expected output | B8: Formula-driven campaign table with revenue, margin, conversion, status and error controls.
A9: Alignment | B9: K3 · A2
A10: Status | B10: Completed example

Sheet Prompt_Log
A1: Prompt_ID | B1: Purpose | C1: Prompt | D1: Grounding | E1: Reviewer | F1: Status
A2: P06-01 | B2: Build and Audit Excel Formulas with Copilot | C2: Goal: From Campaign_Data, calculate revenue, cost, margin, conversion and return rates using formulas. Define the denominator for each rate. Check 96 source records and handle zero denominators explicitly. Context: You work for Lumina Living Pte Ltd on SW-2026, the Sustainable Workspace Launch. HR, Marketing, Finance and Operations share one evidence trail. Launch is planned for 1 October 2026; budget SGD 18,000; target 120 qualified enquiries. Source: Lumina-Business-Data.xlsx. Use your own reviewed prior-lab files first; scenario/ contains supplied fallback examples. Expectations: Save Lumina-Analysis.xlsx. Record source version, verified facts, unresolved questions and reviewer in Lumina-Living-Lab-06.xlsx. Keep projectSW-2026 and action IDsA01–A04 unchanged. Label every output Draft until reviewed; record actual app actions separately. | D2: Attached lab files only | E2: Learner | F2: Verified

Sheet Evidence_Register
A1: Evidence_ID | B1: Artifact | C1: Source | D1: Check | E1: Result | F1: Owner | G1: Notes
A2: E01 | D2: Source and scope verified | E2: PASS | F2: Learner
A3: E02 | D3: Quantitative claims checked | E3: PASS | F3: Learner
A4: E03 | D4: Sensitive data reviewed | E4: PASS | F4: Learner
A5: E04 | D5: Human approval completed | E5: PASS | F5: Learner

Sheet Acceptance_Check
A1: Criterion | B1: Evidence | C1: Status | D1: Reviewer
A2: All derived columns use auditable formulas, zero denominators are handled intentionally and the Controls sheet contains no unexplained errors. | B2: See Evidence_Register | C2: PASS | D2: Learner

Sheet Campaign_Data
A1: Record_ID | B1: Month | C1: Region | D1: Channel | E1: Product | F1: Impressions | G1: Clicks | H1: Orders | I1: Revenue | J1: Cost | K1: Returns | L1: Target_Revenue | M1: Margin | N1: Margin_Percent | O1: Conversion_Rate | P1: Return_Rate | Q1: Target_Status
A2: CMP-0001 | B2: Jan | C2: North | D2: Web | E2: Ergo Desk | F2: 3500 | G2: 122 | H2: 10 | I2: 1500 | J2: 765 | K2: 0 | L2: 8500 | M2: =I2-J2 -> 735 | N2: =IFERROR(M2/I2,0) -> 0.49 | O2: =IFERROR(H2/F2,0) -> 0.0028571429 | P2: =IFERROR(K2/H2,0) -> 0 | Q2: =IF(AND(N2>=Assumptions!$B$2,O2>=Assumptions!$B$3),"On Target","Review") -> Review
A3: CMP-0002 | B3: Feb | C3: North | D3: Web | E3: Ergo Desk | F3: 3673 | G3: 150 | H3: 15 | I3: 3225 | J3: 1789.88 | K3: 3 | L3: 10300 | M3: =I3-J3 -> 1435.12 | N3: =IFERROR(M3/I3,0) -> 0.44499845 | O3: =IFERROR(H3/F3,0) -> 0.0040838552 | P3: =IFERROR(K3/H3,0) -> 0.2 | Q3: =IF(AND(N3>=Assumptions!$B$2,O3>=Assumptions!$B$3),"On Target","Review") -> Review
A4: CMP-0003 | B4: Mar | C4: North | D4: Web | E4: Ergo Desk | F4: 3846 | G4: 180 | H4: 21 | I4: 5880 | J4: 3528 | K4: 6 | L4: 12100 | M4: =I4-J4 -> 2352 | N4: =IFERROR(M4/I4,0) -> 0.4 | O4: =IFERROR(H4/F4,0) -> 0.0054602184 | P4: =IFERROR(K4/H4,0) -> 0.28571429 | Q4: =IF(AND(N4>=Assumptions!$B$2,O4>=Assumptions!$B$3),"On Target","Review") -> Review
A5: CMP-0004 | B5: Apr | C5: South | D5: Web | E5: Ergo Desk | F5: 4019 | G5: 213 | H5: 28 | I5: 9660 | J5: 4926.6 | K5: 9 | L5: 13900 | M5: =I5-J5 -> 4733.4 | N5: =IFERROR(M5/I5,0) -> 0.49 | O5: =IFERROR(H5/F5,0) -> 0.0069669072 | P5: =IFERROR(K5/H5,0) -> 0.32142857 | Q5: =IF(AND(N5>=Assumptions!$B$2,O5>=Assumptions!$B$3),"On Target","Review") -> Review
A6: CMP-0005 | B6: May | C6: South | D6: Web | E6: Ergo Desk | F6: 4192 | G6: 247 | H6: 37 | I6: 5550 | J6: 3080.25 | K6: 12 | L6: 8500 | M6: =I6-J6 -> 2469.75 | N6: =IFERROR(M6/I6,0) -> 0.445 | O6: =IFERROR(H6/F6,0) -> 0.0088263359 | P6: =IFERROR(K6/H6,0) -> 0.32432432 | Q6: =IF(AND(N6>=Assumptions!$B$2,O6>=Assumptions!$B$3),"On Target","Review") -> Review
A7: CMP-0006 | B7: Jun | C7: South | D7: Partner | E7: Ergo Desk | F7: 4365 | G7: 283 | H7: 25 | I7: 5375 | J7: 3225 | K7: 6 | L7: 10300 | M7: =I7-J7 -> 2150 | N7: =IFERROR(M7/I7,0) -> 0.4 | O7: =IFERROR(H7/F7,0) -> 0.0057273769 | P7: =IFERROR(K7/H7,0) -> 0.24 | Q7: =IF(AND(N7>=Assumptions!$B$2,O7>=Assumptions!$B$3),"On Target","Review") -> Review
A8: CMP-0007 | B8: Jan | C8: East | D8: Partner | E8: Ergo Desk | F8: 4538 | G8: 158 | H8: 16 | I8: 4480 | J8: 2284.8 | K8: 0 | L8: 12100 | M8: =I8-J8 -> 2195.2 | N8: =IFERROR(M8/I8,0) -> 0.49 | O8: =IFERROR(H8/F8,0) -> 0.0035257823 | P8: =IFERROR(K8/H8,0) -> 0 | Q8: =IF(AND(N8>=Assumptions!$B$2,O8>=Assumptions!$B$3),"On Target","Review") -> Review
A9: CMP-0008 | B9: Feb | C9: East | D9: Partner | E9: Task Chair | F9: 4711 | G9: 193 | H9: 23 | I9: 7935 | J9: 4403.93 | K9: 5 | L9: 13900 | M9: =I9-J9 -> 3531.07 | N9: =IFERROR(M9/I9,0) -> 0.44499937 | O9: =IFERROR(H9/F9,0) -> 0.0048821906 | P9: =IFERROR(K9/H9,0) -> 0.2173913 | Q9: =IF(AND(N9>=Assumptions!$B$2,O9>=Assumptions!$B$3),"On Target","Review") -> Review
A10: CMP-0009 | B10: Mar | C10: East | D10: Partner | E10: Task Chair | F10: 4884 | G10: 229 | H10: 30 | I10: 4500 | J10: 2700 | K10: 2 | L10: 8500 | M10: =I10-J10 -> 1800 | N10: =IFERROR(M10/I10,0) -> 0.4 | O10: =IFERROR(H10/F10,0) -> 0.0061425061 | P10: =IFERROR(K10/H10,0) -> 0.066666667 | Q10: =IF(AND(N10>=Assumptions!$B$2,O10>=Assumptions!$B$3),"On Target","Review") -> Review
A11: CMP-0010 | B11: Apr | C11: West | D11: Partner | E11: Task Chair | F11: 5057 | G11: 268 | H11: 40 | I11: 8600 | J11: 4386 | K11: 13 | L11: 10300 | M11: =I11-J11 -> 4214 | N11: =IFERROR(M11/I11,0) -> 0.49 | O11: =IFERROR(H11/F11,0) -> 0.007909828 | P11: =IFERROR(K11/H11,0) -> 0.325 | Q11: =IF(AND(N11>=Assumptions!$B$2,O11>=Assumptions!$B$3),"On Target","Review") -> Review
A12: CMP-0011 | B12: May | C12: West | D12: Retail | E12: Task Chair | F12: 5230 | G12: 308 | H12: 27 | I12: 7560 | J12: 4195.8 | K12: 0 | L12: 12100 | M12: =I12-J12 -> 3364.2 | N12: =IFERROR(M12/I12,0) -> 0.445 | O12: =IFERROR(H12/F12,0) -> 0.0051625239 | P12: =IFERROR(K12/H12,0) -> 0 | Q12: =IF(AND(N12>=Assumptions!$B$2,O12>=Assumptions!$B$3),"On Target","Review") -> Review
A13: CMP-0012 | B13: Jun | C13: West | D13: Retail | E13: Task Chair | F13: 5403 | G13: 351 | H13: 36 | I13: 12420 | J13: 7452 | K13: 7 | L13: 13900 | M13: =I13-J13 -> 4968 | N13: =IFERROR(M13/I13,0) -> 0.4 | O13: =IFERROR(H13/F13,0) -> 0.006662965 | P13: =IFERROR(K13/H13,0) -> 0.19444444 | Q13: =IF(AND(N13>=Assumptions!$B$2,O13>=Assumptions!$B$3),"On Target","Review") -> Review
... A97: CMP-0096 | B97: Jun | C97: West | D97: Events | E97: Task Chair | F97: 5935 | G97: 385 | H97: 34 | I97: 11730 | J97: 7038 | K97: 9 | L97: 13900 | M97: =I97-J97 -> 4692 | N97: =IFERROR(M97/I97,0) -> 0.4 | O97: =IFERROR(H97/F97,0) -> 0.0057287279 | P97: =IFERROR(K97/H97,0) -> 0.26470588 | Q97: =IF(AND(N97>=Assumptions!$B$2,O97>=Assumptions!$B$3),"On Target","Review") -> Review

Sheet Assumptions
A1: Assumption | B1: Value | C1: Purpose
A2: Target_Margin | B2: 0.32 | C2: On-target threshold
A3: Target_Conversion | B3: 0.04 | C3: Conversion threshold
A4: High_Return_Rate | B4: 0.08 | C4: Review threshold

Sheet Controls
A1: Control | B1: Result | C1: Expected | D1: Status
A2: Record count | B2: =COUNTA(Campaign_Data!A2:A97) -> 96 | C2: 96 | D2: =IF(B2=C2,"PASS","REVIEW") -> PASS
A3: Blank keys | B3: =COUNTBLANK(Campaign_Data!A2:A97) -> 0 | C3: 0 | D3: =IF(B3=C3,"PASS","REVIEW") -> PASS
A4: Negative revenue | B4: =COUNTIF(Campaign_Data!I2:I97,"<0") -> 0 | C4: 0 | D4: =IF(B4=C4,"PASS","REVIEW") -> PASS
