Workbook

Sheet Campaign_Data
A1: Record_ID | B1: Month | C1: Region | D1: Channel | E1: Product | F1: Impressions | G1: Clicks | H1: Orders | I1: Revenue | J1: Cost | K1: Returns | L1: Target_Revenue
A2: CMP-0001 | B2: Jan | C2: North | D2: Web | E2: Ergo Desk | F2: 3500 | G2: 122 | H2: 10 | I2: 1500 | J2: 765 | K2: 0 | L2: 8500
A3: CMP-0002 | B3: Feb | C3: North | D3: Web | E3: Ergo Desk | F3: 3673 | G3: 150 | H3: 15 | I3: 3225 | J3: 1789.88 | K3: 3 | L3: 10300
A4: CMP-0003 | B4: Mar | C4: North | D4: Web | E4: Ergo Desk | F4: 3846 | G4: 180 | H4: 21 | I4: 5880 | J4: 3528 | K4: 6 | L4: 12100
A5: CMP-0004 | B5: Apr | C5: South | D5: Web | E5: Ergo Desk | F5: 4019 | G5: 213 | H5: 28 | I5: 9660 | J5: 4926.6 | K5: 9 | L5: 13900
A6: CMP-0005 | B6: May | C6: South | D6: Web | E6: Ergo Desk | F6: 4192 | G6: 247 | H6: 37 | I6: 5550 | J6: 3080.25 | K6: 12 | L6: 8500
A7: CMP-0006 | B7: Jun | C7: South | D7: Partner | E7: Ergo Desk | F7: 4365 | G7: 283 | H7: 25 | I7: 5375 | J7: 3225 | K7: 6 | L7: 10300
A8: CMP-0007 | B8: Jan | C8: East | D8: Partner | E8: Ergo Desk | F8: 4538 | G8: 158 | H8: 16 | I8: 4480 | J8: 2284.8 | K8: 0 | L8: 12100
A9: CMP-0008 | B9: Feb | C9: East | D9: Partner | E9: Task Chair | F9: 4711 | G9: 193 | H9: 23 | I9: 7935 | J9: 4403.93 | K9: 5 | L9: 13900
A10: CMP-0009 | B10: Mar | C10: East | D10: Partner | E10: Task Chair | F10: 4884 | G10: 229 | H10: 30 | I10: 4500 | J10: 2700 | K10: 2 | L10: 8500
A11: CMP-0010 | B11: Apr | C11: West | D11: Partner | E11: Task Chair | F11: 5057 | G11: 268 | H11: 40 | I11: 8600 | J11: 4386 | K11: 13 | L11: 10300
A12: CMP-0011 | B12: May | C12: West | D12: Retail | E12: Task Chair | F12: 5230 | G12: 308 | H12: 27 | I12: 7560 | J12: 4195.8 | K12: 0 | L12: 12100
A13: CMP-0012 | B13: Jun | C13: West | D13: Retail | E13: Task Chair | F13: 5403 | G13: 351 | H13: 36 | I13: 12420 | J13: 7452 | K13: 7 | L13: 13900
... A97: CMP-0096 | B97: Jun | C97: West | D97: Events | E97: Task Chair | F97: 5935 | G97: 385 | H97: 34 | I97: 11730 | J97: 7038 | K97: 9 | L97: 13900

Sheet Monthly
A1: Month | B1: Revenue_SGD | C1: Cost_SGD | D1: Margin_SGD
A2: Jan | B2: =SUMIF(Campaign_Data!B$2:B$97,A2,Campaign_Data!I$2:I$97) -> 90150 | C2: =SUMIF(Campaign_Data!B$2:B$97,A2,Campaign_Data!J$2:J$97) -> 45976.5 | D2: =B2-C2 -> 44173.5
A3: Feb | B3: =SUMIF(Campaign_Data!B$2:B$97,A3,Campaign_Data!I$2:I$97) -> 145565 | C3: =SUMIF(Campaign_Data!B$2:B$97,A3,Campaign_Data!J$2:J$97) -> 80788.61 | D3: =B3-C3 -> 64776.39
A4: Mar | B4: =SUMIF(Campaign_Data!B$2:B$97,A4,Campaign_Data!I$2:I$97) -> 130880 | C4: =SUMIF(Campaign_Data!B$2:B$97,A4,Campaign_Data!J$2:J$97) -> 78528 | D4: =B4-C4 -> 52352
A5: Apr | B5: =SUMIF(Campaign_Data!B$2:B$97,A5,Campaign_Data!I$2:I$97) -> 189070 | C5: =SUMIF(Campaign_Data!B$2:B$97,A5,Campaign_Data!J$2:J$97) -> 96425.7 | D5: =B5-C5 -> 92644.3
A6: May | B6: =SUMIF(Campaign_Data!B$2:B$97,A6,Campaign_Data!I$2:I$97) -> 159920 | C6: =SUMIF(Campaign_Data!B$2:B$97,A6,Campaign_Data!J$2:J$97) -> 88755.6 | D6: =B6-C6 -> 71164.4
A7: Jun | B7: =SUMIF(Campaign_Data!B$2:B$97,A7,Campaign_Data!I$2:I$97) -> 217705 | C7: =SUMIF(Campaign_Data!B$2:B$97,A7,Campaign_Data!J$2:J$97) -> 130623 | D7: =B7-C7 -> 87082

Sheet Channels
A1: Channel | B1: Revenue_SGD | C1: Cost_SGD | D1: Margin_SGD
A2: Web | B2: =SUMIF(Campaign_Data!D$2:D$97,A2,Campaign_Data!I$2:I$97) -> 191300 | C2: =SUMIF(Campaign_Data!D$2:D$97,A2,Campaign_Data!J$2:J$97) -> 106755.61 | D2: =B2-C2 -> 84544.39
A3: Partner | B3: =SUMIF(Campaign_Data!D$2:D$97,A3,Campaign_Data!I$2:I$97) -> 214860 | C3: =SUMIF(Campaign_Data!D$2:D$97,A3,Campaign_Data!J$2:J$97) -> 119870.34 | D3: =B3-C3 -> 94989.66
A4: Retail | B4: =SUMIF(Campaign_Data!D$2:D$97,A4,Campaign_Data!I$2:I$97) -> 253330 | C4: =SUMIF(Campaign_Data!D$2:D$97,A4,Campaign_Data!J$2:J$97) -> 141918.68 | D4: =B4-C4 -> 111411.32
A5: Events | B5: =SUMIF(Campaign_Data!D$2:D$97,A5,Campaign_Data!I$2:I$97) -> 273800 | C5: =SUMIF(Campaign_Data!D$2:D$97,A5,Campaign_Data!J$2:J$97) -> 152552.78 | D5: =B5-C5 -> 121247.22

Sheet HR_Readiness
A1: Department | B1: Assigned | C1: Trained | D1: Outstanding | E1: Completion
A2: HR | B2: 12 | C2: 10 | D2: =B2-C2 -> 2 | E2: =IFERROR(C2/B2,0) -> 0.83333333
A3: Marketing | B3: 16 | C3: 14 | D3: =B3-C3 -> 2 | E3: =IFERROR(C3/B3,0) -> 0.875
A4: Finance | B4: 8 | C4: 8 | D4: =B4-C4 -> 0 | E4: =IFERROR(C4/B4,0) -> 1
A5: Operations | B5: 20 | C5: 15 | D5: =B5-C5 -> 5 | E5: =IFERROR(C5/B5,0) -> 0.75
A6: Total | B6: =SUM(B2:B5) -> 56 | C6: =SUM(C2:C5) -> 47 | D6: =SUM(D2:D5) -> 9 | E6: =IFERROR(C6/B6,0) -> 0.83928571

Sheet Dashboard
A1: Metric | B1: Value | C1: Source
A2: Revenue_SGD | B2: =SUM(Campaign_Data!I2:I97) -> 933290 | C2: 96 records Jan–Jun2026
A3: Cost_SGD | B3: =SUM(Campaign_Data!J2:J97) -> 521097.41 | C3: Campaign_Data J2:J97
A4: Margin_SGD | B4: =B2-B3 -> 412192.59 | C4: Revenue minus cost, not net profit
A5: Training_completion | B5: =HR_Readiness!E6 -> 0.83928571 | C5: 47 of56 staff; simulated7Sep
A6: Record_count | B6: =COUNTA(Campaign_Data!A2:A97) -> 96 | C6: Expected96

Sheet Action_Register
A1: Action_ID | B1: Project_ID | C1: Department | D1: Action | E1: Owner | F1: Due_date | G1: Status | H1: Evidence | I1: Last_review
A2: A01 | B2: SW-2026 | C2: HR | D2: Train nine remaining staff | E2: Aisha Tan | F2: 2026-09-24 | G2: In progress | H2: Learner to add actual artifact link | I2: 2026-09-07
A3: A02 | B3: SW-2026 | C3: Marketing | D3: Review claims and launch copy | E3: Daniel Lim | F3: 2026-09-23 | G3: Open | H3: Learner to add actual artifact link | I3: 2026-09-07
A4: A03 | B4: SW-2026 | C4: Finance | D4: Review budget and calculation evidence | E4: Mei Chen | F4: 2026-09-25 | G4: Open | H4: Learner to add actual artifact link | I4: 2026-09-07
A5: A04 | B5: SW-2026 | C5: Operations | D5: Check damaged-item routing and readiness | E5: Harish Rao | F5: 2026-09-25 | G5: Open | H5: Learner to add actual artifact link | I5: 2026-09-07
