Workbook

Sheet Sales_Data
A1: Record_ID | B1: Month | C1: Region | D1: Channel | E1: Product | F1: Impressions | G1: Clicks | H1: Orders | I1: Revenue | J1: Cost | K1: Returns | L1: Target_Revenue | M1: Margin | N1: Margin_Rate | O1: Revenue_Variance
A2: CMP-0001 | B2: Jan | C2: North | D2: Web | E2: Ergo Desk | F2: 3500 | G2: 122 | H2: 10 | I2: 1500 | J2: 765 | K2: 0 | L2: 8500 | M2: =I2-J2 -> 735 | N2: =IF(I2=0,0,M2/I2) -> 0.49 | O2: =I2-L2 -> -7000
A3: CMP-0002 | B3: Feb | C3: North | D3: Web | E3: Ergo Desk | F3: 3673 | G3: 150 | H3: 15 | I3: 3225 | J3: 1789.88 | K3: 3 | L3: 10300 | M3: =I3-J3 -> 1435.12 | N3: =IF(I3=0,0,M3/I3) -> 0.44499845 | O3: =I3-L3 -> -7075
A4: CMP-0003 | B4: Mar | C4: North | D4: Web | E4: Ergo Desk | F4: 3846 | G4: 180 | H4: 21 | I4: 5880 | J4: 3528 | K4: 6 | L4: 12100 | M4: =I4-J4 -> 2352 | N4: =IF(I4=0,0,M4/I4) -> 0.4 | O4: =I4-L4 -> -6220
A5: CMP-0004 | B5: Apr | C5: South | D5: Web | E5: Ergo Desk | F5: 4019 | G5: 213 | H5: 28 | I5: 9660 | J5: 4926.6 | K5: 9 | L5: 13900 | M5: =I5-J5 -> 4733.4 | N5: =IF(I5=0,0,M5/I5) -> 0.49 | O5: =I5-L5 -> -4240
A6: CMP-0005 | B6: May | C6: South | D6: Web | E6: Ergo Desk | F6: 4192 | G6: 247 | H6: 37 | I6: 5550 | J6: 3080.25 | K6: 12 | L6: 8500 | M6: =I6-J6 -> 2469.75 | N6: =IF(I6=0,0,M6/I6) -> 0.445 | O6: =I6-L6 -> -2950
A7: CMP-0006 | B7: Jun | C7: South | D7: Partner | E7: Ergo Desk | F7: 4365 | G7: 283 | H7: 25 | I7: 5375 | J7: 3225 | K7: 6 | L7: 10300 | M7: =I7-J7 -> 2150 | N7: =IF(I7=0,0,M7/I7) -> 0.4 | O7: =I7-L7 -> -4925
A8: CMP-0007 | B8: Jan | C8: East | D8: Partner | E8: Ergo Desk | F8: 4538 | G8: 158 | H8: 16 | I8: 4480 | J8: 2284.8 | K8: 0 | L8: 12100 | M8: =I8-J8 -> 2195.2 | N8: =IF(I8=0,0,M8/I8) -> 0.49 | O8: =I8-L8 -> -7620
A9: CMP-0008 | B9: Feb | C9: East | D9: Partner | E9: Task Chair | F9: 4711 | G9: 193 | H9: 23 | I9: 7935 | J9: 4403.93 | K9: 5 | L9: 13900 | M9: =I9-J9 -> 3531.07 | N9: =IF(I9=0,0,M9/I9) -> 0.44499937 | O9: =I9-L9 -> -5965
A10: CMP-0009 | B10: Mar | C10: East | D10: Partner | E10: Task Chair | F10: 4884 | G10: 229 | H10: 30 | I10: 4500 | J10: 2700 | K10: 2 | L10: 8500 | M10: =I10-J10 -> 1800 | N10: =IF(I10=0,0,M10/I10) -> 0.4 | O10: =I10-L10 -> -4000
A11: CMP-0010 | B11: Apr | C11: West | D11: Partner | E11: Task Chair | F11: 5057 | G11: 268 | H11: 40 | I11: 8600 | J11: 4386 | K11: 13 | L11: 10300 | M11: =I11-J11 -> 4214 | N11: =IF(I11=0,0,M11/I11) -> 0.49 | O11: =I11-L11 -> -1700
A12: CMP-0011 | B12: May | C12: West | D12: Retail | E12: Task Chair | F12: 5230 | G12: 308 | H12: 27 | I12: 7560 | J12: 4195.8 | K12: 0 | L12: 12100 | M12: =I12-J12 -> 3364.2 | N12: =IF(I12=0,0,M12/I12) -> 0.445 | O12: =I12-L12 -> -4540
A13: CMP-0012 | B13: Jun | C13: West | D13: Retail | E13: Task Chair | F13: 5403 | G13: 351 | H13: 36 | I13: 12420 | J13: 7452 | K13: 7 | L13: 13900 | M13: =I13-J13 -> 4968 | N13: =IF(I13=0,0,M13/I13) -> 0.4 | O13: =I13-L13 -> -1480
... A97: CMP-0096 | B97: Jun | C97: West | D97: Events | E97: Task Chair | F97: 5935 | G97: 385 | H97: 34 | I97: 11730 | J97: 7038 | K97: 9 | L97: 13900 | M97: =I97-J97 -> 4692 | N97: =IF(I97=0,0,M97/I97) -> 0.4 | O97: =I97-L97 -> -2170

Sheet Monthly_Finance
A1: Month | B1: Revenue | C1: Cost | D1: Margin | E1: Target | F1: Variance | G1: Margin_Rate | H1: MoM_Revenue
A2: Jan | B2: =SUMIF(Sales_Data!B2:B97,A2,Sales_Data!I2:I97) -> 90150 | C2: =SUMIF(Sales_Data!B2:B97,A2,Sales_Data!J2:J97) -> 45976.5 | D2: =B2-C2 -> 44173.5 | E2: =SUMIF(Sales_Data!B2:B97,A2,Sales_Data!L2:L97) -> 164800 | F2: =B2-E2 -> -74650 | G2: =IF(B2=0,0,D2/B2) -> 0.49 | H2: N/A
A3: Feb | B3: =SUMIF(Sales_Data!B2:B97,A3,Sales_Data!I2:I97) -> 145565 | C3: =SUMIF(Sales_Data!B2:B97,A3,Sales_Data!J2:J97) -> 80788.61 | D3: =B3-C3 -> 64776.39 | E3: =SUMIF(Sales_Data!B2:B97,A3,Sales_Data!L2:L97) -> 193600 | F3: =B3-E3 -> -48035 | G3: =IF(B3=0,0,D3/B3) -> 0.44499976 | H3: =IF(B2=0,0,B3/B2-1) -> 0.61469773
A4: Mar | B4: =SUMIF(Sales_Data!B2:B97,A4,Sales_Data!I2:I97) -> 130880 | C4: =SUMIF(Sales_Data!B2:B97,A4,Sales_Data!J2:J97) -> 78528 | D4: =B4-C4 -> 52352 | E4: =SUMIF(Sales_Data!B2:B97,A4,Sales_Data!L2:L97) -> 164800 | F4: =B4-E4 -> -33920 | G4: =IF(B4=0,0,D4/B4) -> 0.4 | H4: =IF(B3=0,0,B4/B3-1) -> -0.10088277
A5: Apr | B5: =SUMIF(Sales_Data!B2:B97,A5,Sales_Data!I2:I97) -> 189070 | C5: =SUMIF(Sales_Data!B2:B97,A5,Sales_Data!J2:J97) -> 96425.7 | D5: =B5-C5 -> 92644.3 | E5: =SUMIF(Sales_Data!B2:B97,A5,Sales_Data!L2:L97) -> 193600 | F5: =B5-E5 -> -4530 | G5: =IF(B5=0,0,D5/B5) -> 0.49 | H5: =IF(B4=0,0,B5/B4-1) -> 0.44460575
A6: May | B6: =SUMIF(Sales_Data!B2:B97,A6,Sales_Data!I2:I97) -> 159920 | C6: =SUMIF(Sales_Data!B2:B97,A6,Sales_Data!J2:J97) -> 88755.6 | D6: =B6-C6 -> 71164.4 | E6: =SUMIF(Sales_Data!B2:B97,A6,Sales_Data!L2:L97) -> 164800 | F6: =B6-E6 -> -4880 | G6: =IF(B6=0,0,D6/B6) -> 0.445 | H6: =IF(B5=0,0,B6/B5-1) -> -0.1541757
A7: Jun | B7: =SUMIF(Sales_Data!B2:B97,A7,Sales_Data!I2:I97) -> 217705 | C7: =SUMIF(Sales_Data!B2:B97,A7,Sales_Data!J2:J97) -> 130623 | D7: =B7-C7 -> 87082 | E7: =SUMIF(Sales_Data!B2:B97,A7,Sales_Data!L2:L97) -> 193600 | F7: =B7-E7 -> 24105 | G7: =IF(B7=0,0,D7/B7) -> 0.4 | H7: =IF(B6=0,0,B7/B6-1) -> 0.36133692

Sheet Channel_Finance
A1: Channel | B1: Revenue | C1: Cost | D1: Margin | E1: Orders | F1: Revenue_per_Order
A2: Web | B2: =SUMIF(Sales_Data!D2:D97,A2,Sales_Data!I2:I97) -> 191300 | C2: =SUMIF(Sales_Data!D2:D97,A2,Sales_Data!J2:J97) -> 106755.61 | D2: =B2-C2 -> 84544.39 | E2: =SUMIF(Sales_Data!D2:D97,A2,Sales_Data!H2:H97) -> 829 | F2: =IF(E2=0,0,B2/E2) -> 230.75995
A3: Partner | B3: =SUMIF(Sales_Data!D2:D97,A3,Sales_Data!I2:I97) -> 214860 | C3: =SUMIF(Sales_Data!D2:D97,A3,Sales_Data!J2:J97) -> 119870.34 | D3: =B3-C3 -> 94989.66 | E3: =SUMIF(Sales_Data!D2:D97,A3,Sales_Data!H2:H97) -> 915 | F3: =IF(E3=0,0,B3/E3) -> 234.81967
A4: Retail | B4: =SUMIF(Sales_Data!D2:D97,A4,Sales_Data!I2:I97) -> 253330 | C4: =SUMIF(Sales_Data!D2:D97,A4,Sales_Data!J2:J97) -> 141918.68 | D4: =B4-C4 -> 111411.32 | E4: =SUMIF(Sales_Data!D2:D97,A4,Sales_Data!H2:H97) -> 999 | F4: =IF(E4=0,0,B4/E4) -> 253.58358
A5: Events | B5: =SUMIF(Sales_Data!D2:D97,A5,Sales_Data!I2:I97) -> 273800 | C5: =SUMIF(Sales_Data!D2:D97,A5,Sales_Data!J2:J97) -> 152552.78 | D5: =B5-C5 -> 121247.22 | E5: =SUMIF(Sales_Data!D2:D97,A5,Sales_Data!H2:H97) -> 1002 | F5: =IF(E5=0,0,B5/E5) -> 273.25349

Sheet Scenarios
A1: Scenario | B1: Revenue_change_assumption | C1: Revenue | D1: Cost_ratio_assumption | E1: Cost | F1: Margin
A2: Downside | B2: -0.1 | C2: =Monthly_Finance!B7*(1+B2) -> 195934.5 | D2: =SUM(Monthly_Finance!C2:C7)/SUM(Monthly_Finance!B2:B7) -> 0.55834458 | E2: =C2*D2 -> 109398.97 | F2: =C2-E2 -> 86535.535
A3: Base | B3: 0 | C3: =Monthly_Finance!B7*(1+B3) -> 217705 | D3: =SUM(Monthly_Finance!C2:C7)/SUM(Monthly_Finance!B2:B7) -> 0.55834458 | E3: =C3*D3 -> 121554.41 | F3: =C3-E3 -> 96150.594
A4: Upside | B4: 0.1 | C4: =Monthly_Finance!B7*(1+B4) -> 239475.5 | D4: =SUM(Monthly_Finance!C2:C7)/SUM(Monthly_Finance!B2:B7) -> 0.55834458 | E4: =C4*D4 -> 133709.85 | F4: =C4-E4 -> 105765.65

Sheet Read_Me
A1: Lumina Living SW-2026 | B1: Synthetic company finance training sample
A2: Grain | B2: One monthly region/channel/product sales summary; NOT one invoice
A3: Sales definition | B3: Revenue is sales value in SGD; Orders is order count
A4: Cost definition | B4: Illustrative recorded direct costs; no overhead, tax or cash-flow ledger
A5: Margin definition | B5: Revenue minus recorded cost; NOT net profit
A6: Period | B6: Jan–Jun 2026; October campaign is a separate plan
A7: Targets | B7: Synthetic per-record targets, aggregated with SUMIF
A8: Zero denominators | B8: Sample formula returns0; flag zero revenue/orders separately before interpretation
A9: Scenarios | B9: Assumed +/-10% revenue; historical blended cost ratio held constant; not a prediction
A10: Reconciliation | B10: Revenue933290; Cost521097.41; Margin412192.59;96rows
A11: Copilot task | B11: Explain formula logic, generate financial charts, cite ranges, challenge unsupported causes
A12: Sample status | B12: Prepared worked example; not a captured Copilot response
